rnacorex/CLGStructure.py
rnacorex/FuncInformation.py
rnacorex/StrucInformation.py
rnacorex/__init__.py
rnacorex/miRNetClassifier.py
rnacorex/utils.py
rnacorex-0.1.4.dist-info/licenses/LICENSE.txt
rnacorex-0.1.4.dist-info/METADATA
rnacorex-0.1.4.dist-info/WHEEL
rnacorex-0.1.4.dist-info/top_level.txt
rnacorex-0.1.4.dist-info/RECORD
