Metadata-Version: 2.4
Name: RNACOREX
Version: 0.1.4
Summary: RNA Coregulation Network Explorer and Classifier
Author-email: "Oviedo-Madrid, Aitor" <aoviedomadr@unav.es>, "Gonzalez-Gomariz, Jose" <jgonzalezgom@unav.es>, "Armananzas, Ruben" <rarmananzas@unav.es>
License-File: LICENSE.txt
Requires-Dist: numpy<2.0
Requires-Dist: pandas
Requires-Dist: scipy
Requires-Dist: matplotlib
Requires-Dist: networkx
Requires-Dist: joblib
Requires-Dist: tqdm
Requires-Dist: scikit-learn
Requires-Dist: gdown
Dynamic: license-file
